setup.cfg
setup.py
i3_tree/__init__.py
i3_tree.egg-info/PKG-INFO
i3_tree.egg-info/SOURCES.txt
i3_tree.egg-info/dependency_links.txt
i3_tree.egg-info/requires.txt
i3_tree.egg-info/top_level.txt