Metadata-Version: 1.0
Name: i3-tree
Version: 0.2
Summary: Convenient Python lib to manipulate an i3 WM tree
Home-page: http://github.com/mota/i3-tree
Author: Pierre Wacrenier
Author-email: mota@souitom.org
License: ISC
Platform: UNKNOWN
